{
  "__comment__": "AUTO-GENERATED FILE, DO NOT ADD NEW KEYS (it's ok to change values)!",
  "fadd.s": "fpu",
  "fsub.s": "fpu",
  "fmul.s": "fpu",
  "fdiv.s": "fpu",
  "fsgnj.s": "fpu",
  "fsgnjn.s": "fpu",
  "fsgnjx.s": "fpu",
  "fmin.s": "fpu",
  "fmax.s": "fpu",
  "fsqrt.s": "fpu",
  "fle.s": "fpu",
  "flt.s": "fpu",
  "feq.s": "fpu",
  "fcvt.w.s": "fpu",
  "fcvt.wu.s": "fpu",
  "fmv.x.w": "fpu",
  "fclass.s": "fpu",
  "fcvt.s.w": "fpu",
  "fcvt.s.wu": "fpu",
  "fmv.w.x": "fpu",
  "flw": "lsu",
  "fsw": "lsu",
  "fmadd.s": "fpu",
  "fmsub.s": "fpu",
  "fnmsub.s": "fpu",
  "fnmadd.s": "fpu"
}
